{"_id":"/media/tvshows/Top Gear/Season 20/Top Gear - S20E01 - Episode 1 HDTV-720p.mkv","file":"/media/tvshows/Top Gear/Season 20/Top Gear - S20E01 - Episode 1 HDTV-720p.mkv","DB":"4BaCjCxnf","footprintId":"J2vU2ZvGVk","hasClosedCaptions":false,"container":"mkv","scannerReads":{"ffProbeRead":"success"},"ffProbeData":{"format":{"filename":"/media/tvshows/Top Gear/Season 20/Top Gear - S20E01 - Episode 1 HDTV-720p.mkv","nb_streams":2,"nb_programs":0,"format_name":"matroska,webm","format_long_name":"Matroska / WebM","start_time":"0.000000","duration":"3770.794000","size":"984693001","bit_rate":"2089094","probe_score":100,"tags":{"encoder":"libebml v1.4.1 + libmatroska v1.6.2","creation_time":"2021-01-12T20:08:35.000000Z"}},"streams":[{"codec_name":"hevc","codec_type":"video","tags":{"BPS-eng":"1925751","DURATION-eng":"01:02:50.720000000","NUMBER_OF_FRAMES-eng":"97878","NUMBER_OF_BYTES-eng":"907683687","_STATISTICS_WRITING_APP-eng":"mkvmerge v52.0.0 ('Secret For The Mad') 64-bit","_STATISTICS_WRITING_DATE_UTC-eng":"2021-01-12 20:08:35","_STATISTICS_TAGS-eng":"BPS DURATION NUMBER_OF_FRAMES NUMBER_OF_BYTES"},"avg_frame_rate":"25/1","width":1280,"height":720},{"codec_name":"aac","codec_type":"audio","channels":2,"tags":{"BPS-eng":"160570","DURATION-eng":"01:02:50.794000000","NUMBER_OF_FRAMES-eng":"176756","NUMBER_OF_BYTES-eng":"75684769","_STATISTICS_WRITING_APP-eng":"mkvmerge v52.0.0 ('Secret For The Mad') 64-bit","_STATISTICS_WRITING_DATE_UTC-eng":"2021-01-12 20:08:35","_STATISTICS_TAGS-eng":"BPS DURATION NUMBER_OF_FRAMES NUMBER_OF_BYTES"},"avg_frame_rate":"0/0"}]},"file_size":939.0764245986938,"video_resolution":"720p","fileMedium":"video","video_codec_name":"hevc","audio_codec_name":"","lastPluginDetails":"none","createdAt":1688735187319,"bit_rate":2089094,"duration":3770,"statSync":{"mtimeMs":1688729400000,"ctimeMs":1688729400000,"atime":"2023-07-07T11:30:00.000Z","mtime":"2023-07-07T11:30:00.000Z","ctime":"2023-07-07T11:30:00.000Z"},"HealthCheck":"Success","TranscodeDecisionMaker":"Queued","lastHealthCheckDate":1688736461113,"holdUntil":0,"lastTranscodeDate":0,"bumped":false,"history":"","oldSize":0,"newSize":0,"videoStreamIndex":0}