{"_id":"/media/tvshows/Top Gear/Season 22/Top Gear - S22E08 - Episode 8 WEBDL-720p.mkv","file":"/media/tvshows/Top Gear/Season 22/Top Gear - S22E08 - Episode 8 WEBDL-720p.mkv","DB":"4BaCjCxnf","footprintId":"c4ry-JKam","hasClosedCaptions":false,"container":"mkv","scannerReads":{"ffProbeRead":"success"},"ffProbeData":{"format":{"filename":"/media/tvshows/Top Gear/Season 22/Top Gear - S22E08 - Episode 8 WEBDL-720p.mkv","nb_streams":3,"nb_programs":0,"format_name":"matroska,webm","format_long_name":"Matroska / WebM","start_time":"-0.021000","duration":"4343.669000","size":"3259602844","bit_rate":"6003409","probe_score":100,"tags":{"ENCODER":"Lavf60.3.100"}},"streams":[{"codec_name":"h264","codec_type":"video","tags":{"language":"eng","BPS-eng":"5870254","DURATION-eng":"01:12:23.600000000","NUMBER_OF_FRAMES-eng":"108590","NUMBER_OF_BYTES-eng":"3187254700","_STATISTICS_WRITING_APP-eng":"mkvmerge v51.0.0 ('I Wish') 64-bit","_STATISTICS_WRITING_DATE_UTC-eng":"2020-12-30 10:34:26","_STATISTICS_TAGS-eng":"BPS DURATION NUMBER_OF_FRAMES NUMBER_OF_BYTES","DURATION":"01:12:23.600000000"},"avg_frame_rate":"25/1","width":1280,"height":720},{"codec_name":"aac","codec_type":"audio","channels":2,"tags":{"language":"eng","title":"English","BPS-eng":"224000","DURATION-eng":"01:12:23.648000000","NUMBER_OF_FRAMES-eng":"135739","NUMBER_OF_BYTES-eng":"121622144","_STATISTICS_WRITING_APP-eng":"mkvmerge v51.0.0 ('I Wish') 64-bit","_STATISTICS_WRITING_DATE_UTC-eng":"2020-12-30 10:34:26","_STATISTICS_TAGS-eng":"BPS DURATION NUMBER_OF_FRAMES NUMBER_OF_BYTES","ENCODER":"Lavc60.3.100 aac","DURATION":"01:12:23.669000000"},"avg_frame_rate":"0/0"},{"codec_name":"subrip","codec_type":"subtitle","tags":{"language":"eng","title":"English (SDH)","BPS-eng":"90","DURATION-eng":"01:11:30.000000000","NUMBER_OF_FRAMES-eng":"1392","NUMBER_OF_BYTES-eng":"48733","_STATISTICS_WRITING_APP-eng":"mkvmerge v51.0.0 ('I Wish') 64-bit","_STATISTICS_WRITING_DATE_UTC-eng":"2020-12-30 10:34:26","_STATISTICS_TAGS-eng":"BPS DURATION NUMBER_OF_FRAMES NUMBER_OF_BYTES","DURATION":"01:11:47.067000000"},"avg_frame_rate":"0/0","duration":"4343.669000"}]},"file_size":3108.5995140075684,"video_resolution":"720p","fileMedium":"video","video_codec_name":"h264","audio_codec_name":"","lastPluginDetails":"none","createdAt":1688735328156,"bit_rate":6003409,"duration":4343,"statSync":{"mtimeMs":1688735147000,"ctimeMs":1688735147000,"atime":"2023-07-07T13:05:47.000Z","mtime":"2023-07-07T13:05:47.000Z","ctime":"2023-07-07T13:05:47.000Z"},"HealthCheck":"Success","TranscodeDecisionMaker":"Transcode success","lastHealthCheckDate":1688736554834,"holdUntil":0,"lastTranscodeDate":1688735328158,"bumped":false,"history":"","oldSize":3.0827223798260093,"newSize":3.035741712898016,"videoStreamIndex":0,"originalFile":{"_id":"/media/tvshows/Top Gear/Season 22/Top Gear - S22E08 - Episode 8 WEBDL-720p.mkv","file":"/media/tvshows/Top Gear/Season 22/Top Gear - S22E08 - Episode 8 WEBDL-720p.mkv","DB":"4BaCjCxnf","footprintId":"c4ry-JKam","hasClosedCaptions":false,"container":"mkv","scannerReads":{"ffProbeRead":"success"},"ffProbeData":{"format":{"filename":"/media/tvshows/Top Gear/Season 22/Top Gear - S22E08 - Episode 8 WEBDL-720p.mkv","nb_streams":3,"nb_programs":0,"format_name":"matroska,webm","format_long_name":"Matroska / WebM","start_time":"0.000000","duration":"4343.648000","size":"3310047951","bit_rate":"6096346","probe_score":100,"tags":{"encoder":"libebml v1.4.0 + libmatroska v1.6.2"}},"streams":[{"codec_name":"h264","codec_type":"video","tags":{"language":"eng","BPS-eng":"5870254","DURATION-eng":"01:12:23.600000000","NUMBER_OF_FRAMES-eng":"108590","NUMBER_OF_BYTES-eng":"3187254700","_STATISTICS_WRITING_APP-eng":"mkvmerge v51.0.0 ('I Wish') 64-bit","_STATISTICS_WRITING_DATE_UTC-eng":"2020-12-30 10:34:26","_STATISTICS_TAGS-eng":"BPS DURATION NUMBER_OF_FRAMES NUMBER_OF_BYTES"},"avg_frame_rate":"25/1","width":1280,"height":720},{"codec_name":"eac3","codec_type":"audio","bit_rate":"224000","channels":2,"tags":{"language":"eng","title":"English","BPS-eng":"224000","DURATION-eng":"01:12:23.648000000","NUMBER_OF_FRAMES-eng":"135739","NUMBER_OF_BYTES-eng":"121622144","_STATISTICS_WRITING_APP-eng":"mkvmerge v51.0.0 ('I Wish') 64-bit","_STATISTICS_WRITING_DATE_UTC-eng":"2020-12-30 10:34:26","_STATISTICS_TAGS-eng":"BPS DURATION NUMBER_OF_FRAMES NUMBER_OF_BYTES"},"avg_frame_rate":"0/0"},{"codec_name":"subrip","codec_type":"subtitle","tags":{"language":"eng","title":"English (SDH)","BPS-eng":"90","DURATION-eng":"01:11:30.000000000","NUMBER_OF_FRAMES-eng":"1392","NUMBER_OF_BYTES-eng":"48733","_STATISTICS_WRITING_APP-eng":"mkvmerge v51.0.0 ('I Wish') 64-bit","_STATISTICS_WRITING_DATE_UTC-eng":"2020-12-30 10:34:26","_STATISTICS_TAGS-eng":"BPS DURATION NUMBER_OF_FRAMES NUMBER_OF_BYTES"},"avg_frame_rate":"0/0","duration":"4343.648000"}]},"file_size":3156.7077169418335,"video_resolution":"720p","fileMedium":"video","video_codec_name":"h264","audio_codec_name":"","lastPluginDetails":"none","createdAt":1688727472901,"bit_rate":6096346,"duration":4343,"statSync":{"mtimeMs":1688724738000,"ctimeMs":1688724738000,"atime":"2023-07-07T10:12:18.000Z","mtime":"2023-07-07T10:12:18.000Z","ctime":"2023-07-07T10:12:18.000Z"},"HealthCheck":"Success","TranscodeDecisionMaker":"Queued","lastHealthCheckDate":1688727501187,"holdUntil":0,"lastTranscodeDate":0,"bumped":false,"history":"","oldSize":0,"newSize":0,"videoStreamIndex":0}}