{"_id":"/media/tvshows/Top Gear/Season 22/Top Gear - S22E07 - Episode 7 HDTV-1080p.mkv","file":"/media/tvshows/Top Gear/Season 22/Top Gear - S22E07 - Episode 7 HDTV-1080p.mkv","DB":"4BaCjCxnf","footprintId":"PNJJ7npKh","hasClosedCaptions":false,"container":"mkv","scannerReads":{"ffProbeRead":"success"},"ffProbeData":{"format":{"filename":"/media/tvshows/Top Gear/Season 22/Top Gear - S22E07 - Episode 7 HDTV-1080p.mkv","nb_streams":2,"nb_programs":0,"format_name":"mov,mp4,m4a,3gp,3g2,mj2","format_long_name":"QuickTime / MOV","start_time":"0.000000","duration":"3692.175000","size":"870538132","bit_rate":"1886233","probe_score":100,"tags":{"major_brand":"isom","minor_version":"512","compatible_brands":"isomiso2mp41","encoder":"Lavf58.29.100"}},"streams":[{"codec_name":"hevc","codec_type":"video","bit_rate":"1753143","tags":{"language":"und","handler_name":"VideoHandler","vendor_id":"[0][0][0][0]"},"avg_frame_rate":"25/1","duration":"3692.120000","width":1920,"height":1080,"nb_frames":"92303"},{"codec_name":"aac","codec_type":"audio","bit_rate":"128001","channels":2,"tags":{"language":"eng","handler_name":"SoundHandler","vendor_id":"[0][0][0][0]"},"avg_frame_rate":"0/0","duration":"3692.174444","nb_frames":"159009"}]},"file_size":830.2098579406738,"video_resolution":"1080p","fileMedium":"video","video_codec_name":"hevc","audio_codec_name":"","lastPluginDetails":"none","createdAt":1688735141625,"bit_rate":1886233,"duration":3692,"statSync":{"mtimeMs":1688729300000,"ctimeMs":1688729300000,"atime":"2023-07-07T11:28:20.000Z","mtime":"2023-07-07T11:28:20.000Z","ctime":"2023-07-07T11:28:20.000Z"},"HealthCheck":"Success","TranscodeDecisionMaker":"Queued","lastHealthCheckDate":1688735498065,"holdUntil":0,"lastTranscodeDate":0,"bumped":1688735488178,"history":"","oldSize":0,"newSize":0,"videoStreamIndex":0,"lastUpdate":1688735488349}